fnetase/__init__.py
fnetase/calculator.py
fnetase/common.py
fortnet_ase-0.2.1.dist-info/LICENSE
fortnet_ase-0.2.1.dist-info/METADATA
fortnet_ase-0.2.1.dist-info/WHEEL
fortnet_ase-0.2.1.dist-info/top_level.txt
fortnet_ase-0.2.1.dist-info/RECORD
