Metadata-Version: 2.1
Name: fortnet-ase
Version: 0.2.1
Summary: Interfacing Fortnet with the Atomic Simulation Environment
Home-page: https://github.com/vanderhe/fortnet-ase
Author: T. W. van der Heide
Author-email: vanderhe@uni-bremen.de
License: BSD
Platform: any
Classifier: Intended Audience :: Developers
Classifier: License :: OSI Approved :: BSD License
Classifier: Programming Language :: Python :: 3 :: Only
Classifier: Programming Language :: Python :: 3.7
Classifier: Programming Language :: Python :: 3.8
Classifier: Programming Language :: Python :: 3.9
Classifier: Programming Language :: Python :: 3.7
License-File: LICENSE
Requires-Dist: ase
Requires-Dist: fortnet-python
Requires-Dist: h5py
Requires-Dist: hsd
Requires-Dist: numpy
Requires-Dist: pytest
Requires-Dist: setuptools
Requires-Dist: wheel
